README.rst
setup.py
lorm/__init__.py
lorm/db.py
lorm/mysql_pool.py
lorm.egg-info/PKG-INFO
lorm.egg-info/SOURCES.txt
lorm.egg-info/dependency_links.txt
lorm.egg-info/top_level.txt